taocore_human/__init__.py
taocore_human/adapters/__init__.py
taocore_human/adapters/images.py
taocore_human/adapters/video.py
taocore_human/extractors/__init__.py
taocore_human/extractors/base.py
taocore_human/extractors/mediapipe_extractor.py
taocore_human/extractors/scene_extractor.py
taocore_human/extractors/stub.py
taocore_human/nodes/__init__.py
taocore_human/nodes/context.py
taocore_human/nodes/person.py
taocore_human/nodes/temporal.py
taocore_human/pipeline/__init__.py
taocore_human/pipeline/photo_folder.py
taocore_human/pipeline/video_interaction.py
taocore_human/reports/__init__.py
taocore_human/reports/generator.py
taocore_human-0.2.0.dist-info/METADATA
taocore_human-0.2.0.dist-info/WHEEL
taocore_human-0.2.0.dist-info/RECORD
