Metadata-Version: 2.4
Name: taocore-human
Version: 0.2.0
Summary: Image & video pipelines for human behavior and emotion signals using TaoCore
Project-URL: Homepage, https://github.com/daidaitaotao/taocore-human
Project-URL: Repository, https://github.com/daidaitaotao/taocore-human
Author: Xianglong Tao
License: MIT
Keywords: analysis,behavior,emotion,equilibrium,human,image,signals,taocore,video
Classifier: Development Status :: 3 - Alpha
Classifier: Intended Audience :: Developers
Classifier: Intended Audience :: Science/Research
Classifier: License :: OSI Approved :: MIT License
Classifier: Programming Language :: Python :: 3
Classifier: Programming Language :: Python :: 3.9
Classifier: Programming Language :: Python :: 3.10
Classifier: Programming Language :: Python :: 3.11
Classifier: Programming Language :: Python :: 3.12
Classifier: Programming Language :: Python :: 3.13
Classifier: Topic :: Multimedia :: Video
Classifier: Topic :: Scientific/Engineering
Classifier: Topic :: Scientific/Engineering :: Image Processing
Requires-Python: >=3.9
Requires-Dist: numpy>=1.24.0
Requires-Dist: taocore>=0.1.0
Provides-Extra: clip
Requires-Dist: torch>=2.0.0; extra == 'clip'
Requires-Dist: transformers>=4.30.0; extra == 'clip'
Provides-Extra: dev
Requires-Dist: mypy>=1.0.0; extra == 'dev'
Requires-Dist: pytest-cov>=4.0.0; extra == 'dev'
Requires-Dist: pytest>=7.0.0; extra == 'dev'
Requires-Dist: ruff>=0.1.0; extra == 'dev'
Provides-Extra: image
Requires-Dist: pillow>=9.0.0; extra == 'image'
Provides-Extra: mediapipe
Requires-Dist: mediapipe>=0.10.0; extra == 'mediapipe'
Provides-Extra: ml
Requires-Dist: opencv-python>=4.5.0; extra == 'ml'
Requires-Dist: pillow>=9.0.0; extra == 'ml'
Requires-Dist: torch>=2.0.0; extra == 'ml'
Requires-Dist: torchvision>=0.15.0; extra == 'ml'
Requires-Dist: transformers>=4.30.0; extra == 'ml'
Provides-Extra: video
Requires-Dist: opencv-python>=4.5.0; extra == 'video'
Requires-Dist: pillow>=9.0.0; extra == 'video'
